[
  {
    "link": "https://stackoverflow.com/users/1950649/vladimir-mironov",
    "location": "moscow, russia"
  },
  {
    "link": "https://stackoverflow.com/users/286595/zed-0xff",
    "location": "russia"
  },
  {
    "link": "https://stackoverflow.com/users/72178/ks1322",
    "location": "moscow, russia"
  },
  {
    "link": "https://stackoverflow.com/users/274535/yan-sklyarenko",
    "location": "dnipropetrovs&#39;k, ukraine"
  },
  {
    "link": "https://stackoverflow.com/users/706317/zhekakozlov",
    "location": "novosibirsk, russia"
  },
  {
    "link": "https://stackoverflow.com/users/168352/denis-otkidach",
    "location": "moscow, russia"
  },
  {
    "link": "https://stackoverflow.com/users/1026/nickolay",
    "location": "moscow, russia"
  },
  {
    "link": "https://stackoverflow.com/users/24894/kovshenin",
    "location": "moscow, russia"
  },
  {
    "link": "https://stackoverflow.com/users/68998/newtover",
    "location": "st. petersburg, russia"
  },
  {
    "link": "https://stackoverflow.com/users/173677/vladislav-rastrusny",
    "location": "moscow, russia"
  },
  {
    "link": "https://stackoverflow.com/users/171278/culebr%c3%b3n",
    "location": "novosibirsk, russia"
  },
  {
    "link": "https://stackoverflow.com/users/1892060/ainar-g",
    "location": "moscow, russia"
  },
  {
    "link": "https://stackoverflow.com/users/1550807/danil-speransky",
    "location": "saint petersburg, russia"
  },
  {
    "link": "https://stackoverflow.com/users/403105/drtyrsa",
    "location": "russia"
  },
  {
    "link": "https://stackoverflow.com/users/1143825/ilya",
    "location": "ukraine"
  },
  {
    "link": "https://stackoverflow.com/users/80601/eu-ge-ne",
    "location": "dnipropetrovs&#39;k, ukraine"
  },
  {
    "link": "https://stackoverflow.com/users/2700344/leftjoin",
    "location": "kyiv, ukraine"
  },
  {
    "link": "https://stackoverflow.com/users/1490355/singerofthefall",
    "location": "moscow, russia"
  },
  {
    "link": "https://stackoverflow.com/users/1113207/mikhail-gerasimov",
    "location": "russia"
  },
  {
    "link": "https://stackoverflow.com/users/213550/vmatm",
    "location": "saint petersburg, россия"
  },
  {
    "link": "https://stackoverflow.com/users/1532460/awesoon",
    "location": "russia"
  },
  {
    "link": "https://stackoverflow.com/users/406693/roman-bodnarchuk",
    "location": "lviv, ukraine"
  },
  {
    "link": "https://stackoverflow.com/users/186535/antyrat",
    "location": "lviv, ukraine"
  },
  {
    "link": "https://stackoverflow.com/users/568975/mirgorod",
    "location": "ukraine"
  },
  {
    "link": "https://stackoverflow.com/users/885028/aga",
    "location": "togliatty, russia"
  },
  {
    "link": "https://stackoverflow.com/users/997660/nick-krasnov",
    "location": "kursk, russia"
  },
  {
    "link": "https://stackoverflow.com/users/3144601/voddan",
    "location": "saint petersburg, russia"
  },
  {
    "link": "https://stackoverflow.com/users/99024/vanuan",
    "location": "odesa, ukraine"
  },
  {
    "link": "https://stackoverflow.com/users/3651607/andy-korneyev",
    "location": "moscow, russia"
  },
  {
    "link": "https://stackoverflow.com/users/804385/dmitry-pavlov",
    "location": "st. petersburg, russia"
  },
  {
    "link": "https://stackoverflow.com/users/124161/alexey-malistov",
    "location": "moscow, tsentral&#39;niy federal&#39;niy okrug, russia"
  },
  {
    "link": "https://stackoverflow.com/users/159721/narkoz",
    "location": "kyiv, ukraine"
  },
  {
    "link": "https://stackoverflow.com/users/422476/filip-spiridonov",
    "location": "ukraine"
  },
  {
    "link": "https://stackoverflow.com/users/629685/i159",
    "location": "kharkiv, ukraine"
  },
  {
    "link": "https://stackoverflow.com/users/284947/defuz",
    "location": "kiev, ukraine"
  },
  {
    "link": "https://stackoverflow.com/users/4053652/stanislav",
    "location": "st.petersburg"
  },
  {
    "link": "https://stackoverflow.com/users/21501/vladimir-panteleev",
    "location": "chişinău, moldova, eastern europe"
  },
  {
    "link": "https://stackoverflow.com/users/4542359/anton-protopopov",
    "location": "krasnodar, krasnodar krai, russia"
  },
  {
    "link": "https://stackoverflow.com/users/432021/nikolay-shmyrev",
    "location": "moscow, russia"
  },
  {
    "link": "https://stackoverflow.com/users/38975/mike-chaliy",
    "location": "ukraine"
  },
  {
    "link": "https://stackoverflow.com/users/1065190/sergey-k",
    "location": "st.petersburg, russia"
  },
  {
    "link": "https://stackoverflow.com/users/1554034/valex",
    "location": "voronezh, russia"
  },
  {
    "link": "https://stackoverflow.com/users/181671/michael-pakhantsov",
    "location": "dnipropetrovs&#39;k, dnipropetrovsk oblast, ukraine"
  },
  {
    "link": "https://stackoverflow.com/users/1321917/andrey-gordeev",
    "location": "cheboksary, russia"
  },
  {
    "link": "https://stackoverflow.com/users/84507/sergey-vlasov",
    "location": "chelyabinsk, russia"
  },
  {
    "link": "https://stackoverflow.com/users/1979882/vyacheslav",
    "location": "moscow"
  },
  {
    "link": "https://stackoverflow.com/users/444088/andrew",
    "location": "moscow, russia"
  },
  {
    "link": "https://stackoverflow.com/users/67407/maksym-gontar",
    "location": "l&#39;viv, lviv oblast ukraine"
  },
  {
    "link": "https://stackoverflow.com/users/134904/kolypto",
    "location": "ukraine"
  },
  {
    "link": "https://stackoverflow.com/users/746347/mixel",
    "location": "moscow, russia"
  },
  {
    "link": "https://stackoverflow.com/users/2910943/backs",
    "location": "novosibirsk, новосибирская область, россия"
  },
  {
    "link": "https://stackoverflow.com/users/1818688/igor-romanchenko",
    "location": "kyiv, ukraine"
  },
  {
    "link": "https://stackoverflow.com/users/540312/sergei-tachenov",
    "location": "russia"
  },
  {
    "link": "https://stackoverflow.com/users/565518/leonid-shifrin",
    "location": "st. petersburg, russia"
  },
  {
    "link": "https://stackoverflow.com/users/1283124/ilya-ivanov",
    "location": "kiev, kyiv city, ukraine"
  },
  {
    "link": "https://stackoverflow.com/users/624706/sergii-pechenizkyi",
    "location": "ukraine"
  },
  {
    "link": "https://stackoverflow.com/users/188826/siberianguy",
    "location": "russia"
  },
  {
    "link": "https://stackoverflow.com/users/562478/bogdan-verbenets",
    "location": "kyiv, ukraine"
  },
  {
    "link": "https://stackoverflow.com/users/1114926/green",
    "location": "ukraine"
  },
  {
    "link": "https://stackoverflow.com/users/360171/yuriy-rozhovetskiy",
    "location": "kharkiv, ukraine"
  },
  {
    "link": "https://stackoverflow.com/users/169277/ant",
    "location": "st. petersburg, fl, united states"
  },
  {
    "link": "https://stackoverflow.com/users/606586/stecya",
    "location": "lviv, ukraine"
  },
  {
    "link": "https://stackoverflow.com/users/47366/rinat-abdullin",
    "location": "oufa, russia"
  },
  {
    "link": "https://stackoverflow.com/users/1809978/dk14",
    "location": "ukraine"
  },
  {
    "link": "https://stackoverflow.com/users/898042/erjan",
    "location": "astana, kazakhstan"
  },
  {
    "link": "https://stackoverflow.com/users/876298/alex-k",
    "location": "russia, moscow"
  },
  {
    "link": "https://stackoverflow.com/users/545027/eldar-abusalimov",
    "location": "st. petersburg, russia"
  },
  {
    "link": "https://stackoverflow.com/users/93647/oleg-vazhnev",
    "location": "russia"
  },
  {
    "link": "https://stackoverflow.com/users/1977620/max-malysh",
    "location": "moscow, russia"
  },
  {
    "link": "https://stackoverflow.com/users/2176945/anatoliy-nikolaev",
    "location": "russia"
  },
  {
    "link": "https://stackoverflow.com/users/901944/andrey-mikhaylov-lolmaus",
    "location": "moscow, russia"
  },
  {
    "link": "https://stackoverflow.com/users/587415/matrosov-alexander",
    "location": "ukraine"
  },
  {
    "link": "https://stackoverflow.com/users/1847592/egor-skriptunoff",
    "location": "moscow, russia"
  },
  {
    "link": "https://stackoverflow.com/users/445715/andrey-breslav",
    "location": "st. petersburg, russia"
  },
  {
    "link": "https://stackoverflow.com/users/994107/andrey-chernukha",
    "location": "kharkiv, ukraine"
  },
  {
    "link": "https://stackoverflow.com/users/114795/mikhail-korobov",
    "location": "yekaterinburg, russia"
  },
  {
    "link": "https://stackoverflow.com/users/457375/artem-andreev",
    "location": "taganrog, russia"
  },
  {
    "link": "https://stackoverflow.com/users/2501279/guru-stron",
    "location": "st. petersburg, russia"
  },
  {
    "link": "https://stackoverflow.com/users/5380322/cepr0",
    "location": "odessa, ukraine"
  },
  {
    "link": "https://stackoverflow.com/users/1472049/serejja",
    "location": "kyiv, ukraine"
  },
  {
    "link": "https://stackoverflow.com/users/936986/oleg-v-volkov",
    "location": "russia"
  },
  {
    "link": "https://stackoverflow.com/users/436938/sergey-glotov",
    "location": "kazan, russia"
  },
  {
    "link": "https://stackoverflow.com/users/94428/eldar-djafarov",
    "location": "ukraine"
  },
  {
    "link": "https://stackoverflow.com/users/1228514/alex-kucherenko",
    "location": "zhytomyr, ukraine"
  },
  {
    "link": "https://stackoverflow.com/users/4275342/roman-marusyk",
    "location": "ukraine"
  },
  {
    "link": "https://stackoverflow.com/users/1056263/dmytro-danylyk",
    "location": "ukraine"
  },
  {
    "link": "https://stackoverflow.com/users/1929573/valentyn-shybanov",
    "location": "kiev, ukraine"
  },
  {
    "link": "https://stackoverflow.com/users/427457/roman-podlinov",
    "location": "krasnodar, russia"
  },
  {
    "link": "https://stackoverflow.com/users/418507/bdfy",
    "location": "moskva, москва, россия"
  },
  {
    "link": "https://stackoverflow.com/users/143585/denis-tulskiy",
    "location": "karaganda, kazakhstan"
  },
  {
    "link": "https://stackoverflow.com/users/5112433/ilya-chumakov",
    "location": "moscow"
  },
  {
    "link": "https://stackoverflow.com/users/697313/yaroslav-stavnichiy",
    "location": "moscow, russia"
  },
  {
    "link": "https://stackoverflow.com/users/10138734/akina",
    "location": "зеленоград, москва, россия"
  },
  {
    "link": "https://stackoverflow.com/users/261217/mikhail",
    "location": "moscow, russia"
  },
  {
    "link": "https://stackoverflow.com/users/386751/alexander-beletsky",
    "location": "kiev, ukraine"
  },
  {
    "link": "https://stackoverflow.com/users/1627055/vesper",
    "location": "moscow, russia"
  },
  {
    "link": "https://stackoverflow.com/users/76393/ivan-ivanovich-ivanoff",
    "location": "russia"
  },
  {
    "link": "https://stackoverflow.com/users/417810/stanislav-shabalin",
    "location": "russia"
  },
  {
    "link": "https://stackoverflow.com/users/166589/lyubomyr-shaydariv",
    "location": "l&#39;viv, ukraine"
  },
  {
    "link": "https://stackoverflow.com/users/890601/maksym",
    "location": "ukraine"
  },
  {
    "link": "https://stackoverflow.com/users/675678/nekto",
    "location": "moscow, russia"
  },
  {
    "link": "https://stackoverflow.com/users/1646322/ruslan-osmanov",
    "location": "moscow, russia"
  },
  {
    "link": "https://stackoverflow.com/users/3120495/ujeenator",
    "location": "kyiv city, ukraine"
  },
  {
    "link": "https://stackoverflow.com/users/1103561/4ntoine",
    "location": "yekaterinburg, russia"
  },
  {
    "link": "https://stackoverflow.com/users/36498/alamar",
    "location": "st. petersburg, russia"
  },
  {
    "link": "https://stackoverflow.com/users/1010363/dmitryg",
    "location": "russia"
  },
  {
    "link": "https://stackoverflow.com/users/184842/andreyakinshin",
    "location": "russia"
  },
  {
    "link": "https://stackoverflow.com/users/15329/ilya-kochetov",
    "location": "moscow, russia"
  },
  {
    "link": "https://stackoverflow.com/users/448078/mike",
    "location": "kyiv, ukraine"
  },
  {
    "link": "https://stackoverflow.com/users/1007043/gayavat",
    "location": "st. petersburg, russia"
  },
  {
    "link": "https://stackoverflow.com/users/3902472/kosovan",
    "location": "ukraine"
  },
  {
    "link": "https://stackoverflow.com/users/3523579/mikhail-kholodkov",
    "location": "russia"
  },
  {
    "link": "https://stackoverflow.com/users/8060120/brown-bear",
    "location": "санкт-петербург, россия"
  },
  {
    "link": "https://stackoverflow.com/users/177053/vasfed",
    "location": "moscow, russia"
  },
  {
    "link": "https://stackoverflow.com/users/588809/max",
    "location": "ukraine"
  },
  {
    "link": "https://stackoverflow.com/users/1366471/yaroslav-mytkalyk",
    "location": "lviv, ukraine"
  },
  {
    "link": "https://stackoverflow.com/users/241986/boris-treukhov",
    "location": "moscow, russia"
  },
  {
    "link": "https://stackoverflow.com/users/312896/yola",
    "location": "kyiv, ukraine"
  },
  {
    "link": "https://stackoverflow.com/users/4025095/myst",
    "location": "moscow, russia"
  },
  {
    "link": "https://stackoverflow.com/users/570357/snowbear",
    "location": "kiev, ukraine"
  },
  {
    "link": "https://stackoverflow.com/users/1467858/horgh",
    "location": "russia"
  },
  {
    "link": "https://stackoverflow.com/users/70293/alexander-artemenko",
    "location": "moscow, russia"
  },
  {
    "link": "https://stackoverflow.com/users/472270/barmaley",
    "location": "moscow"
  },
  {
    "link": "https://stackoverflow.com/users/74089/nikita-fedyashev",
    "location": "kyiv, ukraine"
  },
  {
    "link": "https://stackoverflow.com/users/1022007/artem-vyshniakov",
    "location": "kharkiv, ukraine"
  },
  {
    "link": "https://stackoverflow.com/users/2914140/coolmind",
    "location": "moscow, россия"
  },
  {
    "link": "https://stackoverflow.com/users/3706693/num8er",
    "location": "ukraine"
  },
  {
    "link": "https://stackoverflow.com/users/323421/sergii-pozharov",
    "location": "kiev, ukraine"
  },
  {
    "link": "https://stackoverflow.com/users/65736/bialix",
    "location": "ukraine"
  },
  {
    "link": "https://stackoverflow.com/users/4317058/sergey-bushmanov",
    "location": "moscow, russia"
  },
  {
    "link": "https://stackoverflow.com/users/2067976/andriy-ivaneyko",
    "location": "l&#39;viv, ukraine"
  },
  {
    "link": "https://stackoverflow.com/users/5400548/leetwinski",
    "location": "moscow, russia"
  },
  {
    "link": "https://stackoverflow.com/users/206855/zaharpopov",
    "location": "mother russia"
  },
  {
    "link": "https://stackoverflow.com/users/824472/igor-dymov",
    "location": "st. petersburg, russia"
  },
  {
    "link": "https://stackoverflow.com/users/4632019/eugen-konkov",
    "location": "ukraine"
  },
  {
    "link": "https://stackoverflow.com/users/817657/s-webbandit",
    "location": "russia"
  },
  {
    "link": "https://stackoverflow.com/users/1117851/itsnikolay",
    "location": "sochi, krasnodar krai, russia"
  },
  {
    "link": "https://stackoverflow.com/users/2893376/gofr1",
    "location": "russia"
  },
  {
    "link": "https://stackoverflow.com/users/1085940/aleksandr-fedorenko",
    "location": "ukraine"
  },
  {
    "link": "https://stackoverflow.com/users/388427/sergey",
    "location": "russia"
  },
  {
    "link": "https://stackoverflow.com/users/5372400/max-makhrov",
    "location": "odessa, ukraine"
  },
  {
    "link": "https://stackoverflow.com/users/3159253/user3159253",
    "location": "novosibirsk, novosibirsk oblast, russia"
  },
  {
    "link": "https://stackoverflow.com/users/673852/ruslan",
    "location": "st. petersburg, russia"
  },
  {
    "link": "https://stackoverflow.com/users/1503018/sectus",
    "location": "russia"
  },
  {
    "link": "https://stackoverflow.com/users/861388/arheops",
    "location": "kiev, ukraine"
  },
  {
    "link": "https://stackoverflow.com/users/210905/odomontois",
    "location": "volgograd, russia"
  },
  {
    "link": "https://stackoverflow.com/users/290339/akond",
    "location": "ukraine"
  },
  {
    "link": "https://stackoverflow.com/users/446267/%d0%9c%d0%b0%d0%bb%d1%8a-%d0%a1%d0%ba%d1%80%d1%8b%d0%bb%d0%b5%d0%b2%d1%8a",
    "location": "moscow, russia"
  },
  {
    "link": "https://stackoverflow.com/users/1034136/serj-tm",
    "location": "moscow, russia"
  },
  {
    "link": "https://stackoverflow.com/users/2071697/skyboyer",
    "location": "ukraine"
  },
  {
    "link": "https://stackoverflow.com/users/1346161/dmytro",
    "location": "ivano-frankivs&#39;k, ukraine"
  },
  {
    "link": "https://stackoverflow.com/users/1542343/gvlasov",
    "location": "ufa, russia"
  },
  {
    "link": "https://stackoverflow.com/users/3454879/andrew-svetlov",
    "location": "kyiv, ukraine"
  },
  {
    "link": "https://stackoverflow.com/users/12123/begray",
    "location": "russia"
  },
  {
    "link": "https://stackoverflow.com/users/3612353/cn007b",
    "location": "ukraine"
  },
  {
    "link": "https://stackoverflow.com/users/19772/alex-koshelev",
    "location": "russia"
  },
  {
    "link": "https://stackoverflow.com/users/235158/antonal",
    "location": "санкт-петербург, город санкт-петербург, россия"
  },
  {
    "link": "https://stackoverflow.com/users/265712/meze",
    "location": "russia, moscow"
  },
  {
    "link": "https://stackoverflow.com/users/2747511/anton-trunov",
    "location": "saint petersburg, russia"
  },
  {
    "link": "https://stackoverflow.com/users/167739/volodymyr-bezuglyy",
    "location": "ukraine"
  },
  {
    "link": "https://stackoverflow.com/users/3103108/ivan",
    "location": "saint petersburg, russia"
  },
  {
    "link": "https://stackoverflow.com/users/512042/lavrton",
    "location": "russia"
  },
  {
    "link": "https://stackoverflow.com/users/440168/k06a",
    "location": "moscow, russia"
  },
  {
    "link": "https://stackoverflow.com/users/72174/sly",
    "location": "kharkiv, ukraine"
  },
  {
    "link": "https://stackoverflow.com/users/207047/captain-comic",
    "location": "moscow, russia"
  },
  {
    "link": "https://stackoverflow.com/users/1213285/oleg-gordiichuk",
    "location": "l&#39;viv, ukraine"
  },
  {
    "link": "https://stackoverflow.com/users/1341058/vbart",
    "location": "moscow, russia"
  },
  {
    "link": "https://stackoverflow.com/users/450466/mediator",
    "location": "ukraine"
  },
  {
    "link": "https://stackoverflow.com/users/4612064/boris-serebrov",
    "location": "ukraine"
  },
  {
    "link": "https://stackoverflow.com/users/1182653/viktor-latypov",
    "location": "st. petersburg, russia"
  },
  {
    "link": "https://stackoverflow.com/users/352708/slava-semushin",
    "location": "novosibirsk, russia"
  },
  {
    "link": "https://stackoverflow.com/users/313902/loislo",
    "location": "st. petersburg, russia"
  },
  {
    "link": "https://stackoverflow.com/users/497132/artem",
    "location": "russia"
  },
  {
    "link": "https://stackoverflow.com/users/607874/jose-rui-santos",
    "location": "moscow, russia"
  },
  {
    "link": "https://stackoverflow.com/users/1328439/dmitri-chubarov",
    "location": "novosibirsk, russia"
  },
  {
    "link": "https://stackoverflow.com/users/2315602/lisyarus",
    "location": "st. petersburg, russia"
  },
  {
    "link": "https://stackoverflow.com/users/1430927/tomilov-anatoliy",
    "location": "russia"
  },
  {
    "link": "https://stackoverflow.com/users/1032167/varren",
    "location": "saint petersburg, russia"
  },
  {
    "link": "https://stackoverflow.com/users/781048/serge-seletskyy",
    "location": "odessa, ukraine"
  },
  {
    "link": "https://stackoverflow.com/users/6053654/commercial-suicide",
    "location": "sankt-peterburg, санкт-петербург, россия"
  },
  {
    "link": "https://stackoverflow.com/users/90859/usercontrol",
    "location": "kiev, ukraine"
  },
  {
    "link": "https://stackoverflow.com/users/460298/dmitry",
    "location": "moscow, russia"
  },
  {
    "link": "https://stackoverflow.com/users/1349754/timur-fayzrakhmanov",
    "location": "russia"
  },
  {
    "link": "https://stackoverflow.com/users/1607485/nikita-kukushkin",
    "location": "moscow, russia"
  },
  {
    "link": "https://stackoverflow.com/users/6678/leonid-shevtsov",
    "location": "dnipropetrovsk, ukraine"
  },
  {
    "link": "https://stackoverflow.com/users/4969827/sergey-shustikov",
    "location": "kyiv, ukraine"
  },
  {
    "link": "https://stackoverflow.com/users/1098230/kolmar",
    "location": "moscow, russia"
  },
  {
    "link": "https://stackoverflow.com/users/3211932/dhilt",
    "location": "st. petersburg, russia"
  },
  {
    "link": "https://stackoverflow.com/users/471149/michael-nesterenko",
    "location": "ukraine"
  },
  {
    "link": "https://stackoverflow.com/users/3459206/alex-salauyou",
    "location": "moscow, russia"
  },
  {
    "link": "https://stackoverflow.com/users/749622/cory-danielson",
    "location": "st. petersburg, fl, usa"
  },
  {
    "link": "https://stackoverflow.com/users/2881286/grundy",
    "location": "тула, тульская область, россия"
  },
  {
    "link": "https://stackoverflow.com/users/80851/gmile",
    "location": "kiev, ukraine"
  },
  {
    "link": "https://stackoverflow.com/users/2715393/vaviloff",
    "location": "krasnoyarsk, russia"
  },
  {
    "link": "https://stackoverflow.com/users/276640/kusanagi",
    "location": "dnepropetrovsk, dnipropetrovsk oblast, ukraine"
  },
  {
    "link": "https://stackoverflow.com/users/73103/eugene-morozov",
    "location": "moscow, russia"
  },
  {
    "link": "https://stackoverflow.com/users/6219979/serg",
    "location": "nizhny novgorod, nizhny novgorod oblast, russia"
  },
  {
    "link": "https://stackoverflow.com/users/458850/nill",
    "location": "saint petersburg, russia"
  },
  {
    "link": "https://stackoverflow.com/users/5630778/slava-utesinov",
    "location": "moscow, russia"
  },
  {
    "link": "https://stackoverflow.com/users/2878550/dmitry",
    "location": "moscow, russia"
  },
  {
    "link": "https://stackoverflow.com/users/751641/denis-kutlubaev",
    "location": "moscow, russia"
  },
  {
    "link": "https://stackoverflow.com/users/159874/4ndrew",
    "location": "st. petersburg, russia"
  },
  {
    "link": "https://stackoverflow.com/users/2170527/yugr",
    "location": "moscow, russia"
  },
  {
    "link": "https://stackoverflow.com/users/1211187/marat-tanalin",
    "location": "moscow, russia"
  },
  {
    "link": "https://stackoverflow.com/users/1716560/ktretyak",
    "location": "kyiv, місто київ, ukraine"
  },
  {
    "link": "https://stackoverflow.com/users/255363/kirilloid",
    "location": "russia"
  },
  {
    "link": "https://stackoverflow.com/users/69777/daniel-ohara",
    "location": "moscow, russia"
  },
  {
    "link": "https://stackoverflow.com/users/3627387/sardorbek-imomaliev",
    "location": "russia"
  },
  {
    "link": "https://stackoverflow.com/users/53481/okutane",
    "location": "saint petersburg, russia"
  },
  {
    "link": "https://stackoverflow.com/users/249690/bobrovsky",
    "location": "omsk, russia"
  },
  {
    "link": "https://stackoverflow.com/users/2110496/vp-arth",
    "location": "novosibirsk, russia"
  },
  {
    "link": "https://stackoverflow.com/users/3461397/oleg-cherednik",
    "location": "st. petersburg, russia"
  },
  {
    "link": "https://stackoverflow.com/users/548473/grigory-kislin",
    "location": "st. petersburg, russia"
  },
  {
    "link": "https://stackoverflow.com/users/11299053/yevgen-gorbunkov",
    "location": "kyiv, ukraine"
  },
  {
    "link": "https://stackoverflow.com/users/2038768/mikhail-vladimirov",
    "location": "moscow, russia"
  },
  {
    "link": "https://stackoverflow.com/users/1199711/zabavsky",
    "location": "l&#39;viv, ukraine"
  },
  {
    "link": "https://stackoverflow.com/users/1477076/burning-legion",
    "location": "ukraine"
  },
  {
    "link": "https://stackoverflow.com/users/1112963/zon",
    "location": "perm&#39;, russia"
  },
  {
    "link": "https://stackoverflow.com/users/1206301/alexei-kaigorodov",
    "location": "novosibirsk, russia"
  },
  {
    "link": "https://stackoverflow.com/users/531179/ulidtko",
    "location": "kiev, ukraine"
  },
  {
    "link": "https://stackoverflow.com/users/1802385/alexander-kurakin",
    "location": "russia"
  },
  {
    "link": "https://stackoverflow.com/users/1731626/sergey",
    "location": "ukraine"
  },
  {
    "link": "https://stackoverflow.com/users/307072/arbejdsgl%c3%a6de",
    "location": "ukraine"
  },
  {
    "link": "https://stackoverflow.com/users/3866447/sam-protsenko",
    "location": "kyiv, ukraine"
  },
  {
    "link": "https://stackoverflow.com/users/94990/nightcoder",
    "location": "togliatty, russia &amp; nyc, usa"
  },
  {
    "link": "https://stackoverflow.com/users/470717/gambit",
    "location": "russia"
  },
  {
    "link": "https://stackoverflow.com/users/881894/alexander-kim",
    "location": "almaty, kazakhstan"
  },
  {
    "link": "https://stackoverflow.com/users/1455661/ilia-rostovtsev",
    "location": "moscow, russia"
  },
  {
    "link": "https://stackoverflow.com/users/183527/oksana",
    "location": "chelyabinsk, russia"
  },
  {
    "link": "https://stackoverflow.com/users/774651/lol4t0",
    "location": "moscow, russia"
  },
  {
    "link": "https://stackoverflow.com/users/6950238/andrii-omelchenko",
    "location": "kyiv city, ukraine"
  },
  {
    "link": "https://stackoverflow.com/users/54606/lo%c3%afc-faure-lacroix",
    "location": "kazan&#39;, russia"
  },
  {
    "link": "https://stackoverflow.com/users/2648942/alexander-yancharuk",
    "location": "moscow, russia"
  },
  {
    "link": "https://stackoverflow.com/users/138290/fake-code-monkey-rashid",
    "location": "st. petersburg, fl"
  },
  {
    "link": "https://stackoverflow.com/users/657487/sandrstar",
    "location": "russia / south korea"
  },
  {
    "link": "https://stackoverflow.com/users/593144/abelisto",
    "location": "ukraine"
  },
  {
    "link": "https://stackoverflow.com/users/1016033/alexey-ten",
    "location": "moscow, russia"
  },
  {
    "link": "https://stackoverflow.com/users/474405/jurka",
    "location": "kiev, ukraine"
  },
  {
    "link": "https://stackoverflow.com/users/4842742/sobolevn",
    "location": "russia"
  },
  {
    "link": "https://stackoverflow.com/users/451518/default-locale",
    "location": "almaty, kazakhstan"
  },
  {
    "link": "https://stackoverflow.com/users/2926641/asiniy",
    "location": "russia"
  },
  {
    "link": "https://stackoverflow.com/users/1313939/sergey-grischyov",
    "location": "saint petersburg, russia"
  },
  {
    "link": "https://stackoverflow.com/users/2790048/nick-volynkin",
    "location": "novosibirsk, russia"
  },
  {
    "link": "https://stackoverflow.com/users/654891/alexey-kukanov",
    "location": "russia"
  },
  {
    "link": "https://stackoverflow.com/users/100237/pingw33n",
    "location": "ukraine"
  },
  {
    "link": "https://stackoverflow.com/users/748259/mikhail-nikalyukin",
    "location": "russia"
  },
  {
    "link": "https://stackoverflow.com/users/235715/alex-burtsev",
    "location": "moscow, russia"
  },
  {
    "link": "https://stackoverflow.com/users/2044355/alexey-b",
    "location": "yekaterinburg, russia"
  },
  {
    "link": "https://stackoverflow.com/users/2165759/omegastripes",
    "location": "saint petersburg, russia"
  },
  {
    "link": "https://stackoverflow.com/users/1024794/maxim-yefremov",
    "location": "russia"
  },
  {
    "link": "https://stackoverflow.com/users/325408/ilya-blokh",
    "location": "perm&#39;, russia"
  },
  {
    "link": "https://stackoverflow.com/users/2712740/seven-phases-max",
    "location": "moscow, russian federation"
  },
  {
    "link": "https://stackoverflow.com/users/269377/maxym",
    "location": "ukraine"
  },
  {
    "link": "https://stackoverflow.com/users/710356/sbichenko",
    "location": "st. petersburg, russia"
  },
  {
    "link": "https://stackoverflow.com/users/162634/victor-sorokin",
    "location": "st. petersburg, russia"
  },
  {
    "link": "https://stackoverflow.com/users/1820286/skuntsel",
    "location": "moscow, russia"
  },
  {
    "link": "https://stackoverflow.com/users/829155/artfeel",
    "location": "kyiv, ukraine"
  },
  {
    "link": "https://stackoverflow.com/users/637740/dmitry-evseev",
    "location": "kyiv, ukraine"
  },
  {
    "link": "https://stackoverflow.com/users/8338/alexey-lebedev",
    "location": "ukraine"
  },
  {
    "link": "https://stackoverflow.com/users/3050466/keenle",
    "location": "odessa, ukraine"
  },
  {
    "link": "https://stackoverflow.com/users/478687/opc0de",
    "location": "ukraine"
  },
  {
    "link": "https://stackoverflow.com/users/222380/andrey-kuznetsov",
    "location": "moscow, russia"
  },
  {
    "link": "https://stackoverflow.com/users/886697/stanislav-bashkyrtsev",
    "location": "st petersburg, russia"
  },
  {
    "link": "https://stackoverflow.com/users/829739/serhii-yakovenko",
    "location": "kyiv, ukraine"
  },
  {
    "link": "https://stackoverflow.com/users/5045688/alexander-petrov",
    "location": "severodvinsk, arkhangelsk oblast, russia"
  },
  {
    "link": "https://stackoverflow.com/users/4251546/vsevolod-goloviznin",
    "location": "russia"
  },
  {
    "link": "https://stackoverflow.com/users/821594/stalk",
    "location": "moscow, russia"
  },
  {
    "link": "https://stackoverflow.com/users/4544823/ken-bekov",
    "location": "kazakhstan"
  },
  {
    "link": "https://stackoverflow.com/users/592186/alexander-zhugastrov",
    "location": "kiev"
  },
  {
    "link": "https://stackoverflow.com/users/1554020/yuri-kilochek",
    "location": "moscow, russia"
  },
  {
    "link": "https://stackoverflow.com/users/299909/mosg",
    "location": "moscow, russia"
  },
  {
    "link": "https://stackoverflow.com/users/3301890/igor",
    "location": "kyiv, ukraine"
  },
  {
    "link": "https://stackoverflow.com/users/1461984/pinepain",
    "location": "kyiv, ukraine"
  },
  {
    "link": "https://stackoverflow.com/users/1175276/bluefire",
    "location": "kyiv, ukraine"
  },
  {
    "link": "https://stackoverflow.com/users/246544/fivell",
    "location": "odessa, ukraine"
  },
  {
    "link": "https://stackoverflow.com/users/147057/max-taldykin",
    "location": "moscow, russia"
  },
  {
    "link": "https://stackoverflow.com/users/2432781/alexander-vasenin",
    "location": "moscow, russia"
  },
  {
    "link": "https://stackoverflow.com/users/113678/datagreed",
    "location": "moscow, russia"
  },
  {
    "link": "https://stackoverflow.com/users/229949/the-joric",
    "location": "kiev, ukraine"
  },
  {
    "link": "https://stackoverflow.com/users/18575/ilya-ryzhenkov",
    "location": "st. petersburg, russia"
  },
  {
    "link": "https://stackoverflow.com/users/102243/konstantin-tenzin",
    "location": "moscow, russia"
  },
  {
    "link": "https://stackoverflow.com/users/513266/victor-deryagin",
    "location": "ukraine"
  },
  {
    "link": "https://stackoverflow.com/users/496825/gor",
    "location": "kharkiv, ukraine"
  },
  {
    "link": "https://stackoverflow.com/users/1950327/glen-swift",
    "location": "kiev, ukraine"
  },
  {
    "link": "https://stackoverflow.com/users/788700/adobe",
    "location": "moscow, russia"
  },
  {
    "link": "https://stackoverflow.com/users/5341877/r-m-n",
    "location": "moscow, russia"
  },
  {
    "link": "https://stackoverflow.com/users/985241/rmagnum2002",
    "location": "moldova, republic of"
  },
  {
    "link": "https://stackoverflow.com/users/343443/abyx",
    "location": "st. petersburg, russia"
  },
  {
    "link": "https://stackoverflow.com/users/572834/alexey-ivanov",
    "location": "st. petersburg, russia"
  },
  {
    "link": "https://stackoverflow.com/users/52317/uzbekjon",
    "location": "moscow, russia"
  },
  {
    "link": "https://stackoverflow.com/users/2513573/adamskywalker",
    "location": "moscow, russia"
  },
  {
    "link": "https://stackoverflow.com/users/1049475/erakitin",
    "location": "moscow, russia"
  },
  {
    "link": "https://stackoverflow.com/users/530339/yuri-stuken",
    "location": "moscow, russia"
  },
  {
    "link": "https://stackoverflow.com/users/1548895/vadim-ovchinnikov",
    "location": "kharkiv, ukraine"
  },
  {
    "link": "https://stackoverflow.com/users/194635/stas",
    "location": "russia"
  },
  {
    "link": "https://stackoverflow.com/users/643393/ixsci",
    "location": "russia, nizhny novgorod"
  },
  {
    "link": "https://stackoverflow.com/users/547242/larry-cinnabar",
    "location": "moldova"
  },
  {
    "link": "https://stackoverflow.com/users/585795/sergey",
    "location": "almaty, kazakhstan"
  },
  {
    "link": "https://stackoverflow.com/users/514382/valentin-kuzub",
    "location": "st. petersburg, russia"
  },
  {
    "link": "https://stackoverflow.com/users/193903/unkulunkulu",
    "location": "moscow, russia"
  },
  {
    "link": "https://stackoverflow.com/users/3777113/roman-doskoch",
    "location": "lviv, lviv oblast, ukraine"
  },
  {
    "link": "https://stackoverflow.com/users/7394871/alexandr-tt",
    "location": "ekaterinburg, russia"
  },
  {
    "link": "https://stackoverflow.com/users/555553/mishadoff",
    "location": "kiev, ukraine"
  },
  {
    "link": "https://stackoverflow.com/users/3190190/victor-bocharsky",
    "location": "kiev, ukraine"
  },
  {
    "link": "https://stackoverflow.com/users/2525067/pinal",
    "location": "moscow, russia"
  },
  {
    "link": "https://stackoverflow.com/users/435904/4e6",
    "location": "russia"
  },
  {
    "link": "https://stackoverflow.com/users/2894369/alex2410",
    "location": "russia"
  },
  {
    "link": "https://stackoverflow.com/users/2923816/lobzik",
    "location": "saint petersburg, russia"
  },
  {
    "link": "https://stackoverflow.com/users/1027367/andrey-sobolev",
    "location": "chelyabinsk, russia"
  },
  {
    "link": "https://stackoverflow.com/users/1542806/andrey-smorodov",
    "location": "russia"
  },
  {
    "link": "https://stackoverflow.com/users/1372866/ashakirov",
    "location": "kazan, казань, russia"
  },
  {
    "link": "https://stackoverflow.com/users/271641/marat",
    "location": "russia"
  },
  {
    "link": "https://stackoverflow.com/users/1010404/igor-shubin",
    "location": "ukraine"
  },
  {
    "link": "https://stackoverflow.com/users/1033448/anton-guryanov",
    "location": "moscow, russia"
  },
  {
    "link": "https://stackoverflow.com/users/186652/sergey-eremin",
    "location": "st. petersburg, russia"
  },
  {
    "link": "https://stackoverflow.com/users/477997/leonidos",
    "location": "russia, moscow"
  },
  {
    "link": "https://stackoverflow.com/users/5328417/arsen",
    "location": "moscow, russia"
  },
  {
    "link": "https://stackoverflow.com/users/4390212/dimasan",
    "location": "kyiv city, ukraine"
  },
  {
    "link": "https://stackoverflow.com/users/2427222/ymonad",
    "location": "russia"
  },
  {
    "link": "https://stackoverflow.com/users/333777/klaster-1",
    "location": "saint petersburg, russia"
  },
  {
    "link": "https://stackoverflow.com/users/1196603/jk1",
    "location": "st. petersburg, russia"
  },
  {
    "link": "https://stackoverflow.com/users/55209/artem-koshelev",
    "location": "moscow, russia"
  },
  {
    "link": "https://stackoverflow.com/users/401450/set",
    "location": "sumy, ukraine"
  },
  {
    "link": "https://stackoverflow.com/users/2709018/myaut",
    "location": "st. petersburg, russia"
  },
  {
    "link": "https://stackoverflow.com/users/1306132/andrey-bushman",
    "location": "moscow, russia"
  },
  {
    "link": "https://stackoverflow.com/users/75284/sasha-koss",
    "location": "russia"
  },
  {
    "link": "https://stackoverflow.com/users/1360544/boris-burkov",
    "location": "moscow, russia"
  },
  {
    "link": "https://stackoverflow.com/users/1749836/shukshin-ivan",
    "location": "gelendzhik, krasnodarskiy kray, russia"
  },
  {
    "link": "https://stackoverflow.com/users/441393/heximal",
    "location": "saint petersburg, russia"
  },
  {
    "link": "https://stackoverflow.com/users/860478/victor-marchuk",
    "location": "russia"
  },
  {
    "link": "https://stackoverflow.com/users/92854/bealex",
    "location": "st. petersburg, russia"
  },
  {
    "link": "https://stackoverflow.com/users/1108484/dmytro-zarezenko",
    "location": "vinnytsya, ukraine"
  },
  {
    "link": "https://stackoverflow.com/users/312725/max-yankov",
    "location": "moscow, russia"
  },
  {
    "link": "https://stackoverflow.com/users/2555999/zuzel",
    "location": "novosibirsk, russia"
  },
  {
    "link": "https://stackoverflow.com/users/7879193/stanislav-kralin",
    "location": "yekaterinburg, russia"
  },
  {
    "link": "https://stackoverflow.com/users/653311/grand",
    "location": "moscow, russia"
  },
  {
    "link": "https://stackoverflow.com/users/13441/sergtk",
    "location": "kyiv, ukraine"
  },
  {
    "link": "https://stackoverflow.com/users/2012219/hbk",
    "location": "ukraine"
  },
  {
    "link": "https://stackoverflow.com/users/909085/mikle-garin",
    "location": "russia"
  },
  {
    "link": "https://stackoverflow.com/users/2308005/medet-tleukabiluly",
    "location": "almaty, kazakhstan"
  },
  {
    "link": "https://stackoverflow.com/users/874027/eugene",
    "location": "kiev, ukraine"
  },
  {
    "link": "https://stackoverflow.com/users/1283474/fedor-gogolev",
    "location": "st. petersburg, russia"
  },
  {
    "link": "https://stackoverflow.com/users/296433/olegas",
    "location": "yaroslavl, russia"
  },
  {
    "link": "https://stackoverflow.com/users/645460/maxim-v-pavlov",
    "location": "kiev, ukraine"
  },
  {
    "link": "https://stackoverflow.com/users/2138959/andrii-litvinov",
    "location": "ukraine"
  },
  {
    "link": "https://stackoverflow.com/users/3239417/vsminkov",
    "location": "novosibirsk, novosibirsk oblast, russia"
  },
  {
    "link": "https://stackoverflow.com/users/185919/java-is-for-desktop",
    "location": "russia"
  },
  {
    "link": "https://stackoverflow.com/users/2000124/rem",
    "location": "kolomna, russia"
  },
  {
    "link": "https://stackoverflow.com/users/2454376/mishik",
    "location": "moscow, russia"
  },
  {
    "link": "https://stackoverflow.com/users/1568530/vladyslav-matviienko",
    "location": "dnipro, днепропетровская область, ukraine"
  },
  {
    "link": "https://stackoverflow.com/users/489403/devmiles-com",
    "location": "kiev, ukraine"
  },
  {
    "link": "https://stackoverflow.com/users/396811/daniel-kluev",
    "location": "vladivostok, russia"
  },
  {
    "link": "https://stackoverflow.com/users/1226354/vyacheslav-shylkin",
    "location": "odessa, ukraine"
  },
  {
    "link": "https://stackoverflow.com/users/257568/artemgr",
    "location": "st. petersburg, russia"
  },
  {
    "link": "https://stackoverflow.com/users/347767/gangabass",
    "location": "irkutsk, russia"
  },
  {
    "link": "https://stackoverflow.com/users/2923345/nalexn",
    "location": "moscow, russia"
  },
  {
    "link": "https://stackoverflow.com/users/34134/snitko",
    "location": "st. petersburg, russia"
  },
  {
    "link": "https://stackoverflow.com/users/226537/jura-gorohovsky",
    "location": "st. petersburg, russia"
  },
  {
    "link": "https://stackoverflow.com/users/200449/gennady-vanin-%d0%93%d0%b5%d0%bd%d0%bd%d0%b0%d0%b4%d0%b8%d0%b9-%d0%92%d0%b0%d0%bd%d0%b8%d0%bd",
    "location": "novosibirsk, russia (новосибирск, россия)"
  },
  {
    "link": "https://stackoverflow.com/users/831314/penartur",
    "location": "moscow, russia"
  },
  {
    "link": "https://stackoverflow.com/users/4858777/valeriy-katkov",
    "location": "yoshkar-ola, russia"
  },
  {
    "link": "https://stackoverflow.com/users/2066428/malex",
    "location": "moscow"
  },
  {
    "link": "https://stackoverflow.com/users/230744/ony",
    "location": "ukraine"
  },
  {
    "link": "https://stackoverflow.com/users/604427/alexvassel",
    "location": "moscow, russia"
  },
  {
    "link": "https://stackoverflow.com/users/1891712/spatz",
    "location": "st. petersburg, russia"
  },
  {
    "link": "https://stackoverflow.com/users/7045114/maksim-ostrovidov",
    "location": "moscow, russia"
  },
  {
    "link": "https://stackoverflow.com/users/397911/jamapag",
    "location": "zhytomyr, ukraine"
  },
  {
    "link": "https://stackoverflow.com/users/298282/yasir-arsanukaev",
    "location": "moscow, россия"
  },
  {
    "link": "https://stackoverflow.com/users/801058/leemour",
    "location": "st. petersburg, russia"
  },
  {
    "link": "https://stackoverflow.com/users/3503026/nfort",
    "location": "moscow"
  },
  {
    "link": "https://stackoverflow.com/users/889941/vladimir",
    "location": "moscow, russia"
  },
  {
    "link": "https://stackoverflow.com/users/1836420/chikabuz",
    "location": "l&#39;viv, ukraine"
  },
  {
    "link": "https://stackoverflow.com/users/848550/vitalii-ponomar",
    "location": "ukraine, kiev"
  },
  {
    "link": "https://stackoverflow.com/users/362350/sto",
    "location": "ukraine"
  },
  {
    "link": "https://stackoverflow.com/users/883970/micnic",
    "location": "moldova"
  },
  {
    "link": "https://stackoverflow.com/users/428563/vsevik",
    "location": "st. petersburg, russia"
  },
  {
    "link": "https://stackoverflow.com/users/1907902/kharandziuk",
    "location": "kyiv, ukraine"
  },
  {
    "link": "https://stackoverflow.com/users/5438212/kokovin-vladislav",
    "location": "tyumen, russia"
  },
  {
    "link": "https://stackoverflow.com/users/3216312/petr",
    "location": "nizhny novgorod, russia"
  },
  {
    "link": "https://stackoverflow.com/users/632516/divers",
    "location": "moscow, russia"
  },
  {
    "link": "https://stackoverflow.com/users/1453505/alexander",
    "location": "ukraine"
  },
  {
    "link": "https://stackoverflow.com/users/639183/ernazm",
    "location": "kharkov, ukraine"
  },
  {
    "link": "https://stackoverflow.com/users/590388/alexey-popkov",
    "location": "nizhny novgorod, russia"
  },
  {
    "link": "https://stackoverflow.com/users/230214/bessarabov",
    "location": "moscow, russia"
  },
  {
    "link": "https://stackoverflow.com/users/977052/vsevolod-dyomkin",
    "location": "kyiv, ukraine"
  },
  {
    "link": "https://stackoverflow.com/users/2363866/creker",
    "location": "russia"
  },
  {
    "link": "https://stackoverflow.com/users/4206079/banzay",
    "location": "ukraine"
  },
  {
    "link": "https://stackoverflow.com/users/3379437/beloo",
    "location": "ukraine"
  },
  {
    "link": "https://stackoverflow.com/users/7637657/alexander-romanov",
    "location": "moscow, russia"
  },
  {
    "link": "https://stackoverflow.com/users/6533/fixpoint",
    "location": "ukraine"
  },
  {
    "link": "https://stackoverflow.com/users/13782669/alex-noname",
    "location": "russia"
  },
  {
    "link": "https://stackoverflow.com/users/449553/msangel",
    "location": "vinnytsya, ukraine"
  },
  {
    "link": "https://stackoverflow.com/users/1052325/reclosedev",
    "location": "russia"
  },
  {
    "link": "https://stackoverflow.com/users/63867/vitaliy-ulantikov",
    "location": "kiev, ukraine"
  },
  {
    "link": "https://stackoverflow.com/users/1771556/vadim-ashikhman",
    "location": "moscow, russia"
  },
  {
    "link": "https://stackoverflow.com/users/4897391/ffeast",
    "location": "moscow, россия"
  },
  {
    "link": "https://stackoverflow.com/users/3846213/eli-korvigo",
    "location": "st. petersburg"
  },
  {
    "link": "https://stackoverflow.com/users/1173020/denis-peplin",
    "location": "volgograd, russia"
  },
  {
    "link": "https://stackoverflow.com/users/4381665/alexander-solonik",
    "location": "moscow"
  },
  {
    "link": "https://stackoverflow.com/users/53658/denis-bazhenov",
    "location": "russia"
  },
  {
    "link": "https://stackoverflow.com/users/801496/hast",
    "location": "kyiv, ukraine"
  },
  {
    "link": "https://stackoverflow.com/users/88165/nikolay-ivanov",
    "location": "st. petersburg, russia"
  },
  {
    "link": "https://stackoverflow.com/users/1762344/evgeny-panasyuk",
    "location": "rostov-na-donu, russia"
  },
  {
    "link": "https://stackoverflow.com/users/440465/anton-gaenko",
    "location": "moscow, russia"
  },
  {
    "link": "https://stackoverflow.com/users/11732/rorick",
    "location": "st. petersburg, russia"
  },
  {
    "link": "https://stackoverflow.com/users/1421254/dmitriusan",
    "location": "ukraine"
  },
  {
    "link": "https://stackoverflow.com/users/111040/sashaeve",
    "location": "kyiv, ukraine"
  },
  {
    "link": "https://stackoverflow.com/users/58146/andrey-tarantsov",
    "location": "novosibirsk, russia"
  },
  {
    "link": "https://stackoverflow.com/users/758648/hck",
    "location": "ukraine, kiev"
  },
  {
    "link": "https://stackoverflow.com/users/1732138/darkwanderer",
    "location": "moscow, russia"
  },
  {
    "link": "https://stackoverflow.com/users/65813/ilya-birman",
    "location": "chelyabinsk, russia"
  },
  {
    "link": "https://stackoverflow.com/users/332311/davs",
    "location": "kharkiv, ukraine"
  },
  {
    "link": "https://stackoverflow.com/users/958370/jin35",
    "location": "russia"
  },
  {
    "link": "https://stackoverflow.com/users/521032/septagram",
    "location": "krasnoyarsk, krasnoyarsk krai, russia"
  },
  {
    "link": "https://stackoverflow.com/users/2702781/nyavro",
    "location": "novosibirsk, russian federation"
  },
  {
    "link": "https://stackoverflow.com/users/1031981/eugene-soldatov",
    "location": "russia"
  },
  {
    "link": "https://stackoverflow.com/users/28121/sudden-def",
    "location": "samara, russia"
  },
  {
    "link": "https://stackoverflow.com/users/5526354/mikhail",
    "location": "vladivostok, russia"
  },
  {
    "link": "https://stackoverflow.com/users/3022273/andrey-shokhin",
    "location": "moscow, russia"
  },
  {
    "link": "https://stackoverflow.com/users/2742717/swift-friday-pie",
    "location": "moscow, russia"
  },
  {
    "link": "https://stackoverflow.com/users/723891/igonato",
    "location": "russia"
  },
  {
    "link": "https://stackoverflow.com/users/2076787/d-side",
    "location": "st. petersburg, russia"
  },
  {
    "link": "https://stackoverflow.com/users/1599260/rost",
    "location": "samara, russia"
  },
  {
    "link": "https://stackoverflow.com/users/27703/shrike",
    "location": "moscow, russia"
  },
  {
    "link": "https://stackoverflow.com/users/1813669/scadge",
    "location": "ukraine"
  },
  {
    "link": "https://stackoverflow.com/users/791619/warhog",
    "location": "russia"
  },
  {
    "link": "https://stackoverflow.com/users/66473/alex-bolotov",
    "location": "ukraine"
  },
  {
    "link": "https://stackoverflow.com/users/1465625/hank",
    "location": "moscow, russia"
  },
  {
    "link": "https://stackoverflow.com/users/27122/dpq",
    "location": "moscow, russia"
  },
  {
    "link": "https://stackoverflow.com/users/1863950/artem-klevtsov",
    "location": "russia"
  },
  {
    "link": "https://stackoverflow.com/users/1208233/yang",
    "location": "russian hill, san francisco, ca, usa"
  },
  {
    "link": "https://stackoverflow.com/users/911419/suncatcher",
    "location": "kyiv city, ukraine"
  },
  {
    "link": "https://stackoverflow.com/users/6498293/david-dale",
    "location": "moscow, russia"
  },
  {
    "link": "https://stackoverflow.com/users/3980/andrew-%d0%90%d0%bd%d0%b4%d1%80%d0%b5%d0%b9-%d0%9b%d0%b8%d1%81%d1%82%d0%be%d1%87%d0%ba%d0%b8%d0%bd",
    "location": "kiev, ukraine"
  },
  {
    "link": "https://stackoverflow.com/users/1093248/sumoanand",
    "location": "st. petersburg, fl"
  },
  {
    "link": "https://stackoverflow.com/users/1920758/nick",
    "location": "russia, moscow"
  },
  {
    "link": "https://stackoverflow.com/users/321215/dmitriy-nesteryuk",
    "location": "zaporiz&#39;ka oblast, ukraine"
  },
  {
    "link": "https://stackoverflow.com/users/534943/styx",
    "location": "kiev, ukraine"
  },
  {
    "link": "https://stackoverflow.com/users/1208512/nkuhta",
    "location": "moscow"
  },
  {
    "link": "https://stackoverflow.com/users/315129/vbezhenar",
    "location": "astana, kazakhstan"
  },
  {
    "link": "https://stackoverflow.com/users/911976/alexk",
    "location": "ukraine"
  },
  {
    "link": "https://stackoverflow.com/users/355491/andrii-nemchenko",
    "location": "kyiv, ukraine"
  },
  {
    "link": "https://stackoverflow.com/users/820813/ku6opr",
    "location": "ukraine"
  },
  {
    "link": "https://stackoverflow.com/users/177605/bniwredyc",
    "location": "moscow, russia"
  },
  {
    "link": "https://stackoverflow.com/users/558018/agentfire",
    "location": "russia"
  },
  {
    "link": "https://stackoverflow.com/users/2559709/alex-zhukovskiy",
    "location": "moscow, russia"
  },
  {
    "link": "https://stackoverflow.com/users/7110799/dmitriy-dumanskiy",
    "location": "kyiv city, ukraine"
  },
  {
    "link": "https://stackoverflow.com/users/282328/poma",
    "location": "moscow, russia"
  },
  {
    "link": "https://stackoverflow.com/users/918233/kyr-dunenkoff",
    "location": "krasnodar, russia"
  },
  {
    "link": "https://stackoverflow.com/users/164925/anton-korobeynikov",
    "location": "st. petersburg, russia"
  },
  {
    "link": "https://stackoverflow.com/users/4891253/oleh-dokuka",
    "location": "ukraine"
  },
  {
    "link": "https://stackoverflow.com/users/369317/denis-kniazhev",
    "location": "kharkiv, ukraine"
  },
  {
    "link": "https://stackoverflow.com/users/362583/bohdan",
    "location": "l&#39;viv, l&#39;viv region, ukraine"
  },
  {
    "link": "https://stackoverflow.com/users/656804/nikolay-fominyh",
    "location": "st. petersburg, russia"
  },
  {
    "link": "https://stackoverflow.com/users/10659910/william-miller",
    "location": "moscow, id, usa"
  },
  {
    "link": "https://stackoverflow.com/users/241552/ibolit",
    "location": "moscow, russia"
  },
  {
    "link": "https://stackoverflow.com/users/7754/squadette",
    "location": "moscow, russia"
  }
]